esource_client_api/__init__.py
esource_client_api/async_/__init__.py
esource_client_api/async_/base_resource.py
esource_client_api/async_/changelog.py
esource_client_api/async_/client.py
esource_client_api/async_/maps.py
esource_client_api/async_/players.py
esource_client_api/async_/session.py
esource_client_api/async_/sports.py
esource_client_api/async_/teams.py
esource_client_api/async_/trading_categories.py
esource_client_api/async_/trading_events.py
esource_client_api/async_/trading_tournaments.py
esource_client_api/models/__init__.py
esource_client_api/models/errors.py
esource_client_api/models/models.py
esource_client_api/sync/__init__.py
esource_client_api/sync/base_resource.py
esource_client_api/sync/changelog.py
esource_client_api/sync/client.py
esource_client_api/sync/maps.py
esource_client_api/sync/players.py
esource_client_api/sync/session.py
esource_client_api/sync/sports.py
esource_client_api/sync/teams.py
esource_client_api/sync/trading_categories.py
esource_client_api/sync/trading_events.py
esource_client_api/sync/trading_tournaments.py
esource_client_api-1.2.0.dist-info/licenses/LICENSE
esource_client_api-1.2.0.dist-info/METADATA
esource_client_api-1.2.0.dist-info/WHEEL
esource_client_api-1.2.0.dist-info/top_level.txt
esource_client_api-1.2.0.dist-info/RECORD
