Metadata-Version: 2.4
Name: esource_client_api
Version: 1.2.0
Summary: Python SDK for the Esource.gg Client API
Author-email: "Esource.gg" <info@esource.gg>
License: MIT
Project-URL: Homepage, https://github.com/Eppop-bet/client-api-sdk
Project-URL: Repository, https://github.com/Eppop-bet/client-api-sdk
Classifier: Programming Language :: Python :: 3
Classifier: Programming Language :: Python :: 3.7
Classifier: Programming Language :: Python :: 3.8
Classifier: Programming Language :: Python :: 3.9
Classifier: Programming Language :: Python :: 3.10
Classifier: Programming Language :: Python :: 3.11
Classifier: Programming Language :: Python :: 3.12
Classifier: Operating System :: OS Independent
Classifier: Intended Audience :: Developers
Classifier: Topic :: Software Development :: Libraries :: Python Modules
Requires-Python: >=3.7
License-File: LICENSE
Requires-Dist: requests>=2.30.0
Requires-Dist: pydantic>=2.0
Requires-Dist: httpx>=0.20.0
Dynamic: license-file
